Metadata-Version: 2.1
Name: hocv
Version: 0.0.7
Summary: Python科学计算大作业
Home-page: https://github.com/swpfY/hocv.git
Author: JQS
Author-email: ink_fishing@protonmail.com
License: UNKNOWN
Platform: UNKNOWN
License-File: LICENSE
